Workbook

Sheet Assumptions
A1: Project Sunrise — budget assumptions
A2: Blue = inputs you can change · yellow = key levers · everything else is calculated.
A4: Assumption | B4: Value | C4: Note
A5: Seats | B5: 80 | C5: Seated covers incl. terrace in season
A6: Opening days per month | B6: 26 | C6: Closed Mondays
A7: Covers per seat per day at full ramp | B7: 3.2 | C7: Vrijdagmarkt achieves 3.6
A8: Average spend per cover (€) | B8: 9.4 | C8: Vrijdagmarkt 2026 average: € 9.10
A9: Month-1 ramp (share of full) | B9: 0.55 | C9: Rises linearly to the month-6 level
A10: Month-6 ramp (share of full) | B10: 0.9 | C10: Then flat, plus growth below
A11: Monthly growth after month 6 | B11: 0.01
A12: Cost of goods (share of revenue) | B12: 0.29 | C12: Beans at internal transfer price
A13: Staff cost per month (€) | B13: 21500 | C13: 6.5 FTE
A14: Rent per month (€) | B14: 4200 | C14: Korenmarkt lease offer
A15: Other running costs per month (€) | B15: 3100 | C15: Utilities, insurance, cleaning, card fees
A16: Opening investment (€) | B16: =Investment!D10 -> 122650 | C16: From the proposal; see Investment

Sheet Investment
A1: Opening investment (€, excl. VAT)
A3: Item | B3: Q1 2027 | C3: Q2 2027 | D3: Total
A4: Fit-out and furniture | B4: 48000 | C4: 6000 | D4: =SUM(B4:C4) -> 54000
A5: Espresso machine and grinders | B5: 22500 | C5: 0 | D5: =SUM(B5:C5) -> 22500
A6: Staff hiring and training | B6: 9000 | C6: 14000 | D6: =SUM(B6:C6) -> 23000
A7: Opening marketing | B7: 3500 | C7: 8500 | D7: =SUM(B7:C7) -> 12000
A8: Contingency rate | B8: 0.1
A9: Contingency | B9: =SUM(B4:B7)*$B$8 -> 8300 | C9: =SUM(C4:C7)*$B$8 -> 2850 | D9: =SUM(B9:C9) -> 11150
A10: Total | B10: =SUM(B4:B7)+B9 -> 91300 | C10: =SUM(C4:C7)+C9 -> 31350 | D10: =SUM(D4:D7)+D9 -> 122650

Sheet Forecast
A1: First 18 months after opening (€)
A3: Month | B3: M1 | C3: M2 | D3: M3 | E3: M4 | F3: M5 | G3: M6 | H3: M7 | I3: M8 | J3: M9 | K3: M10 | L3: M11 | M3: M12 | N3: M13 | O3: M14 | P3: M15 | Q3: M16 | R3: M17 | S3: M18
A4: Ramp | B4: =Assumptions!$B$9+(Assumptions!$B$10-Assumptions!$B$9)*(1-1)/5 -> 0.55 | C4: =Assumptions!$B$9+(Assumptions!$B$10-Assumptions!$B$9)*(2-1)/5 -> 0.62 | D4: =Assumptions!$B$9+(Assumptions!$B$10-Assumptions!$B$9)*(3-1)/5 -> 0.69 | E4: =Assumptions!$B$9+(Assumptions!$B$10-Assumptions!$B$9)*(4-1)/5 -> 0.76 | F4: =Assumptions!$B$9+(Assumptions!$B$10-Assumptions!$B$9)*(5-1)/5 -> 0.83 | G4: =Assumptions!$B$9+(Assumptions!$B$10-Assumptions!$B$9)*(6-1)/5 -> 0.9 | H4: =G4*(1+Assumptions!$B$11) -> 0.909 | I4: =H4*(1+Assumptions!$B$11) -> 0.91809 | J4: =I4*(1+Assumptions!$B$11) -> 0.9272709 | K4: =J4*(1+Assumptions!$B$11) -> 0.93654361 | L4: =K4*(1+Assumptions!$B$11) -> 0.94590905 | M4: =L4*(1+Assumptions!$B$11) -> 0.95536814 | N4: =M4*(1+Assumptions!$B$11) -> 0.96492182 | O4: =N4*(1+Assumptions!$B$11) -> 0.97457104 | ... S4: =R4*(1+Assumptions!$B$11) -> 1.0141425
A5: Covers | B5: =ROUND(Assumptions!$B$5*Assumptions!$B$7*Assumptions!$B$6*B4,0) -> 3661 | C5: =ROUND(Assumptions!$B$5*Assumptions!$B$7*Assumptions!$B$6*C4,0) -> 4127 | D5: =ROUND(Assumptions!$B$5*Assumptions!$B$7*Assumptions!$B$6*D4,0) -> 4593 | E5: =ROUND(Assumptions!$B$5*Assumptions!$B$7*Assumptions!$B$6*E4,0) -> 5059 | F5: =ROUND(Assumptions!$B$5*Assumptions!$B$7*Assumptions!$B$6*F4,0) -> 5524 | G5: =ROUND(Assumptions!$B$5*Assumptions!$B$7*Assumptions!$B$6*G4,0) -> 5990 | H5: =ROUND(Assumptions!$B$5*Assumptions!$B$7*Assumptions!$B$6*H4,0) -> 6050 | I5: =ROUND(Assumptions!$B$5*Assumptions!$B$7*Assumptions!$B$6*I4,0) -> 6111 | ... S5: =ROUND(Assumptions!$B$5*Assumptions!$B$7*Assumptions!$B$6*S4,0) -> 6750
A6: Revenue | B6: =B5*Assumptions!$B$8 -> 34413.4 | C6: =C5*Assumptions!$B$8 -> 38793.8 | D6: =D5*Assumptions!$B$8 -> 43174.2 | E6: =E5*Assumptions!$B$8 -> 47554.6 | F6: =F5*Assumptions!$B$8 -> 51925.6 | G6: =G5*Assumptions!$B$8 -> 56306 | H6: =H5*Assumptions!$B$8 -> 56870 | I6: =I5*Assumptions!$B$8 -> 57443.4 | ... S6: =S5*Assumptions!$B$8 -> 63450
A7: Cost of goods | B7: =-B6*Assumptions!$B$12 -> -9979.886 | C7: =-C6*Assumptions!$B$12 -> -11250.202 | D7: =-D6*Assumptions!$B$12 -> -12520.518 | E7: =-E6*Assumptions!$B$12 -> -13790.834 | F7: =-F6*Assumptions!$B$12 -> -15058.424 | G7: =-G6*Assumptions!$B$12 -> -16328.74 | H7: =-H6*Assumptions!$B$12 -> -16492.3 | I7: =-I6*Assumptions!$B$12 -> -16658.586 | ... S7: =-S6*Assumptions!$B$12 -> -18400.5
A8: Gross margin | B8: =B6+B7 -> 24433.514 | C8: =C6+C7 -> 27543.598 | D8: =D6+D7 -> 30653.682 | E8: =E6+E7 -> 33763.766 | F8: =F6+F7 -> 36867.176 | G8: =G6+G7 -> 39977.26 | H8: =H6+H7 -> 40377.7 | I8: =I6+I7 -> 40784.814 | ... S8: =S6+S7 -> 45049.5
A9: Staff | B9: =-Assumptions!$B$13 -> -21500 | C9: =-Assumptions!$B$13 -> -21500 | D9: =-Assumptions!$B$13 -> -21500 | E9: =-Assumptions!$B$13 -> -21500 | F9: =-Assumptions!$B$13 -> -21500 | G9: =-Assumptions!$B$13 -> -21500 | H9: =-Assumptions!$B$13 -> -21500 | I9: =-Assumptions!$B$13 -> -21500 | ... S9: =-Assumptions!$B$13 -> -21500
A10: Rent | B10: =-Assumptions!$B$14 -> -4200 | C10: =-Assumptions!$B$14 -> -4200 | D10: =-Assumptions!$B$14 -> -4200 | E10: =-Assumptions!$B$14 -> -4200 | F10: =-Assumptions!$B$14 -> -4200 | G10: =-Assumptions!$B$14 -> -4200 | H10: =-Assumptions!$B$14 -> -4200 | I10: =-Assumptions!$B$14 -> -4200 | ... S10: =-Assumptions!$B$14 -> -4200
A11: Other | B11: =-Assumptions!$B$15 -> -3100 | C11: =-Assumptions!$B$15 -> -3100 | D11: =-Assumptions!$B$15 -> -3100 | E11: =-Assumptions!$B$15 -> -3100 | F11: =-Assumptions!$B$15 -> -3100 | G11: =-Assumptions!$B$15 -> -3100 | H11: =-Assumptions!$B$15 -> -3100 | I11: =-Assumptions!$B$15 -> -3100 | ... S11: =-Assumptions!$B$15 -> -3100
A12: Operating result | B12: =SUM(B8:B11) -> -4366.486 | C12: =SUM(C8:C11) -> -1256.402 | D12: =SUM(D8:D11) -> 1853.682 | E12: =SUM(E8:E11) -> 4963.766 | F12: =SUM(F8:F11) -> 8067.176 | G12: =SUM(G8:G11) -> 11177.26 | H12: =SUM(H8:H11) -> 11577.7 | I12: =SUM(I8:I11) -> 11984.814 | ... S12: =SUM(S8:S11) -> 16249.5
A13: Cumulative cash | B13: =-Assumptions!$B$16+B12 -> -127016.49 | C13: =B13+C12 -> -128272.89 | D13: =C13+D12 -> -126419.21 | E13: =D13+E12 -> -121455.44 | F13: =E13+F12 -> -113388.26 | G13: =F13+G12 -> -102211 | H13: =G13+H12 -> -90633.304 | I13: =H13+I12 -> -78648.49 | J13: =I13+J12 -> -66256.562 | ... S13: =R13+S12 -> 64311.712
A15: Break-even month | B15: =IF(COUNTIF(B13:S13,"<0")>=18,"after M18","M"&(COUNTIF(B13:S13,"<0")+1)) -> M14
A16: First month the cumulative cash (after the opening investment) is back above zero.
